odoo8_addon_product_template_book_weight_calculation-8.0.1.0.0-py2.7-nspkg.pth
odoo_addons/product_template_book_weight_calculation/__openerp__.py
odoo_addons/product_template_book_weight_calculation/product_template_book_weight_calculation.py
odoo_addons/product_template_book_weight_calculation/__init__.py
odoo_addons/product_template_book_weight_calculation/README.rst
odoo_addons/product_template_book_weight_calculation/tests/__init__.py
odoo_addons/product_template_book_weight_calculation/tests/test_product_template.py
odoo8_addon_product_template_book_weight_calculation-8.0.1.0.0.dist-info/top_level.txt
odoo8_addon_product_template_book_weight_calculation-8.0.1.0.0.dist-info/WHEEL
odoo8_addon_product_template_book_weight_calculation-8.0.1.0.0.dist-info/RECORD
odoo8_addon_product_template_book_weight_calculation-8.0.1.0.0.dist-info/metadata.json
odoo8_addon_product_template_book_weight_calculation-8.0.1.0.0.dist-info/DESCRIPTION.rst
odoo8_addon_product_template_book_weight_calculation-8.0.1.0.0.dist-info/METADATA
odoo8_addon_product_template_book_weight_calculation-8.0.1.0.0.dist-info/namespace_packages.txt
